odoo/addons/donation_recurring/README.rst
odoo/addons/donation_recurring/__init__.py
odoo/addons/donation_recurring/__manifest__.py
odoo/addons/donation_recurring/uninstall.py
odoo/addons/donation_recurring/demo/donation_recurring_demo.xml
odoo/addons/donation_recurring/i18n/de.po
odoo/addons/donation_recurring/i18n/donation_recurring.pot
odoo/addons/donation_recurring/i18n/es.po
odoo/addons/donation_recurring/i18n/fr.po
odoo/addons/donation_recurring/i18n/it.po
odoo/addons/donation_recurring/models/__init__.py
odoo/addons/donation_recurring/models/donation.py
odoo/addons/donation_recurring/readme/CONFIGURE.rst
odoo/addons/donation_recurring/readme/CONTRIBUTORS.rst
odoo/addons/donation_recurring/readme/DESCRIPTION.rst
odoo/addons/donation_recurring/readme/USAGE.rst
odoo/addons/donation_recurring/security/ir.model.access.csv
odoo/addons/donation_recurring/static/description/icon.png
odoo/addons/donation_recurring/static/description/index.html
odoo/addons/donation_recurring/tests/__init__.py
odoo/addons/donation_recurring/tests/test_recurring_donations.py
odoo/addons/donation_recurring/views/donation.xml
odoo/addons/donation_recurring/wizard/__init__.py
odoo/addons/donation_recurring/wizard/donation_recurring_generate.py
odoo/addons/donation_recurring/wizard/donation_recurring_generate_view.xml
odoo_addon_donation_recurring-16.0.1.1.0.dist-info/METADATA
odoo_addon_donation_recurring-16.0.1.1.0.dist-info/WHEEL
odoo_addon_donation_recurring-16.0.1.1.0.dist-info/top_level.txt
odoo_addon_donation_recurring-16.0.1.1.0.dist-info/RECORD
